odoo/addons/shopfloor_workstation/README.rst
odoo/addons/shopfloor_workstation/__init__.py
odoo/addons/shopfloor_workstation/__manifest__.py
odoo/addons/shopfloor_workstation/demo/shopfloor_workstation_demo.xml
odoo/addons/shopfloor_workstation/i18n/es_AR.po
odoo/addons/shopfloor_workstation/i18n/it.po
odoo/addons/shopfloor_workstation/i18n/shopfloor_workstation.pot
odoo/addons/shopfloor_workstation/models/__init__.py
odoo/addons/shopfloor_workstation/models/shopfloor_workstation.py
odoo/addons/shopfloor_workstation/readme/CONFIGURE.rst
odoo/addons/shopfloor_workstation/readme/CONTRIBUTORS.rst
odoo/addons/shopfloor_workstation/readme/DESCRIPTION.rst
odoo/addons/shopfloor_workstation/security/ir.model.access.csv
odoo/addons/shopfloor_workstation/services/__init__.py
odoo/addons/shopfloor_workstation/services/workstation.py
odoo/addons/shopfloor_workstation/static/description/icon.png
odoo/addons/shopfloor_workstation/static/description/index.html
odoo/addons/shopfloor_workstation/tests/__init__.py
odoo/addons/shopfloor_workstation/tests/test_shopfloor_workstation.py
odoo/addons/shopfloor_workstation/views/shopfloor_workstation.xml
odoo_addon_shopfloor_workstation-16.0.1.0.0.3.dist-info/METADATA
odoo_addon_shopfloor_workstation-16.0.1.0.0.3.dist-info/WHEEL
odoo_addon_shopfloor_workstation-16.0.1.0.0.3.dist-info/top_level.txt
odoo_addon_shopfloor_workstation-16.0.1.0.0.3.dist-info/RECORD
