Metadata-Version: 2.1
Name: odoo-addon-shopfloor-workstation
Version: 16.0.1.0.0.3
Summary: Manage warehouse workstation with barcode scanners
Home-page: https://github.com/OCA/wms
Author: Camptocamp, Odoo Community Association (OCA)
Author-email: support@odoo-community.org
License: AGPL-3
Platform: UNKNOWN
Classifier: Programming Language :: Python
Classifier: Framework :: Odoo
Classifier: Framework :: Odoo :: 16.0
Classifier: License :: OSI Approved :: GNU Affero General Public License v3
Classifier: Development Status :: 4 - Beta
Requires-Python: >=3.10
Requires-Dist: odoo-addon-base-report-to-printer <16.1dev,>=16.0dev
Requires-Dist: odoo-addon-shopfloor <16.1dev,>=16.0dev
Requires-Dist: odoo <16.1dev,>=16.0a
